dailyai/__init__.py
dailyai/pipeline/__init__.py
dailyai/pipeline/aggregators.py
dailyai/pipeline/frame_processor.py
dailyai/pipeline/frames.proto
dailyai/pipeline/frames.py
dailyai/pipeline/merge_pipeline.py
dailyai/pipeline/opeanai_llm_aggregator.py
dailyai/pipeline/openai_frames.py
dailyai/pipeline/pipeline.py
dailyai/pipeline/protobufs/frames_pb2.py
dailyai/serializers/abstract_frame_serializer.py
dailyai/serializers/protobuf_serializer.py
dailyai/services/__init__.py
dailyai/services/ai_services.py
dailyai/services/anthropic_llm_service.py
dailyai/services/azure_ai_services.py
dailyai/services/deepgram_ai_service.py
dailyai/services/deepgram_ai_services.py
dailyai/services/elevenlabs_ai_service.py
dailyai/services/fal_ai_services.py
dailyai/services/fireworks_ai_services.py
dailyai/services/local_stt_service.py
dailyai/services/moondream_ai_service.py
dailyai/services/ollama_ai_services.py
dailyai/services/open_ai_services.py
dailyai/services/openai_api_llm_service.py
dailyai/services/openai_llm_context.py
dailyai/services/playht_ai_service.py
dailyai/services/whisper_ai_services.py
dailyai/services/to_be_updated/__init__.py
dailyai/services/to_be_updated/cloudflare_ai_service.py
dailyai/services/to_be_updated/google_ai_service.py
dailyai/services/to_be_updated/huggingface_ai_service.py
dailyai/services/to_be_updated/mock_ai_service.py
dailyai/storage/__init__.py
dailyai/storage/search.py
dailyai/transports/abstract_transport.py
dailyai/transports/daily_transport.py
dailyai/transports/local_transport.py
dailyai/transports/threaded_transport.py
dailyai/transports/websocket_transport.py
dailyai-0.0.8.dist-info/LICENSE
dailyai-0.0.8.dist-info/METADATA
dailyai-0.0.8.dist-info/WHEEL
dailyai-0.0.8.dist-info/top_level.txt
dailyai-0.0.8.dist-info/RECORD
