Metadata-Version: 2.1
Name: dailyai
Version: 0.0.8
Summary: An open source framework for real-time, multi-modal, conversational AI applications
License: BSD 2-Clause License
Project-URL: Source, https://github.com/daily-co/dailyai
Project-URL: Website, https://daily.co
Keywords: webrtc,audio,video,ai
Classifier: Development Status :: 5 - Production/Stable
Classifier: Intended Audience :: Developers
Classifier: License :: OSI Approved :: BSD License
Classifier: Topic :: Communications :: Conferencing
Classifier: Topic :: Multimedia :: Sound/Audio
Classifier: Topic :: Multimedia :: Video
Classifier: Topic :: Scientific/Engineering :: Artificial Intelligence
Requires-Python: >=3.7
License-File: LICENSE
Requires-Dist: aiohttp ~=3.9.0
Requires-Dist: numpy ~=1.26.0
Requires-Dist: Pillow ~=10.2.0
Requires-Dist: typing-extensions ~=4.10.0
Provides-Extra: anthropic
Requires-Dist: anthropic ~=0.20.0 ; extra == 'anthropic'
Provides-Extra: azure
Requires-Dist: azure-cognitiveservices-speech ~=1.36.0 ; extra == 'azure'
Provides-Extra: daily
Requires-Dist: daily-python ~=0.7.0 ; extra == 'daily'
Provides-Extra: examples
Requires-Dist: python-dotenv ~=1.0.0 ; extra == 'examples'
Requires-Dist: flask ~=3.0.0 ; extra == 'examples'
Requires-Dist: flask-cors ~=4.0.0 ; extra == 'examples'
Provides-Extra: fal
Requires-Dist: fal-client ~=0.2.0 ; extra == 'fal'
Provides-Extra: fireworks
Requires-Dist: openai ~=1.14.0 ; extra == 'fireworks'
Provides-Extra: local
Requires-Dist: pyaudio ~=0.2.0 ; extra == 'local'
Provides-Extra: moondream
Requires-Dist: einops ~=0.7.0 ; extra == 'moondream'
Requires-Dist: timm ~=0.9.0 ; extra == 'moondream'
Requires-Dist: transformers ~=4.39.0 ; extra == 'moondream'
Provides-Extra: openai
Requires-Dist: openai ~=1.14.0 ; extra == 'openai'
Provides-Extra: playht
Requires-Dist: pyht ~=0.0.26 ; extra == 'playht'
Provides-Extra: silero
Requires-Dist: torch ~=2.2.0 ; extra == 'silero'
Requires-Dist: torchaudio ~=2.2.0 ; extra == 'silero'
Provides-Extra: websocket
Requires-Dist: websockets ~=12.0 ; extra == 'websocket'
Provides-Extra: whisper
Requires-Dist: faster-whisper ~=1.0.0 ; extra == 'whisper'
